map2-2.1.1.dist-info/METADATA
map2-2.1.1.dist-info/WHEEL
map2.libs/libxkbcommon-71ae2972.so.0
map2/__init__.py
map2/map2.cpython-311-x86_64-linux-gnu.so
map2-2.1.1.dist-info/RECORD
