Metadata-Version: 2.3
Name: map2
Version: 2.1.1
Author: shiro <shiro@usagi.io>
Author-email: shiro <shiro@usagi.io>
